hypershap/__init__.py
hypershap/hypershap.py
hypershap/surrogate_model.py
hypershap/task.py
hypershap/utils.py
hypershap/games/__init__.py
hypershap/games/ablation.py
hypershap/games/abstract.py
hypershap/games/multi_data.py
hypershap/games/optimizerbias.py
hypershap/games/tunability.py
hypershap-0.0.5.dist-info/METADATA
hypershap-0.0.5.dist-info/WHEEL
hypershap-0.0.5.dist-info/licenses/LICENSE
hypershap-0.0.5.dist-info/RECORD
