Metadata-Version: 2.4
Name: hypershap
Version: 0.0.5
Summary: HyperSHAP is a post-hoc explanation method for hyperparameter optimization.
Project-URL: Homepage, https://automl.github.io/hypershap/
Project-URL: Repository, https://github.com/automl/hypershap
Project-URL: Documentation, https://automl.github.io/hypershap/
Author-email: Marcel Wever <m.wever@ai.uni-hannover.de>
License-File: LICENSE
Keywords: python
Classifier: Intended Audience :: Developers
Classifier: Programming Language :: Python
Classifier: Programming Language :: Python :: 3
Classifier: Programming Language :: Python :: 3.10
Classifier: Programming Language :: Python :: 3.11
Classifier: Programming Language :: Python :: 3.12
Classifier: Programming Language :: Python :: 3.13
Classifier: Topic :: Software Development :: Libraries :: Python Modules
Requires-Python: <4.0,>=3.10
Requires-Dist: configspace>=1.2.1
Requires-Dist: matplotlib>=3.10.5
Requires-Dist: networkx>=3.4.2
Requires-Dist: numpy>=2.2.6
Requires-Dist: scikit-learn>=1.7.1
Requires-Dist: shapiq==1.4.1
